[
 {
  "id": 1101020022,
  "districtId": 1101020,
  "districtName": "SIMEULUE TIMUR",
  "name": "AIR PINANG",
  "postalCode": "23891"
 },
 {
  "id": 1101020023,
  "districtId": 1101020,
  "districtName": "SIMEULUE TIMUR",
  "name": "KUALA MAKMUR",
  "postalCode": "23891"
 },
 {
  "id": 1101020024,
  "districtId": 1101020,
  "districtName": "SIMEULUE TIMUR",
  "name": "GANTING",
  "postalCode": "23891"
 },
 {
  "id": 1101020025,
  "districtId": 1101020,
  "districtName": "SIMEULUE TIMUR",
  "name": "LINGGI",
  "postalCode": "23891"
 },
 {
  "id": 1101020026,
  "districtId": 1101020,
  "districtName": "SIMEULUE TIMUR",
  "name": "LUGU",
  "postalCode": "23891"
 },
 {
  "id": 1101020027,
  "districtId": 1101020,
  "districtName": "SIMEULUE TIMUR",
  "name": "SINABANG",
  "postalCode": "23891"
 },
 {
  "id": 1101020028,
  "districtId": 1101020,
  "districtName": "SIMEULUE TIMUR",
  "name": "SUKA MAJU",
  "postalCode": "24673"
 },
 {
  "id": 1101020029,
  "districtId": 1101020,
  "districtName": "SIMEULUE TIMUR",
  "name": "SUKA KARYA",
  "postalCode": "23891"
 },
 {
  "id": 1101020030,
  "districtId": 1101020,
  "districtName": "SIMEULUE TIMUR",
  "name": "SUKA JAYA",
  "postalCode": "24784"
 },
 {
  "id": 1101020031,
  "districtId": 1101020,
  "districtName": "SIMEULUE TIMUR",
  "name": "AIR DINGIN",
  "postalCode": "23891"
 },
 {
  "id": 1101020032,
  "districtId": 1101020,
  "districtName": "SIMEULUE TIMUR",
  "name": "KOTA BATU",
  "postalCode": "23891"
 },
 {
  "id": 1101020035,
  "districtId": 1101020,
  "districtName": "SIMEULUE TIMUR",
  "name": "SUAK BULUH",
  "postalCode": "23891"
 },
 {
  "id": 1101020036,
  "districtId": 1101020,
  "districtName": "SIMEULUE TIMUR",
  "name": "UJUNG TINGGI",
  "postalCode": "23891"
 },
 {
  "id": 1101020037,
  "districtId": 1101020,
  "districtName": "SIMEULUE TIMUR",
  "name": "PULAU SIUMAT",
  "postalCode": "23891"
 },
 {
  "id": 1101020038,
  "districtId": 1101020,
  "districtName": "SIMEULUE TIMUR",
  "name": "SEFOYAN",
  "postalCode": "23891"
 },
 {
  "id": 1101020039,
  "districtId": 1101020,
  "districtName": "SIMEULUE TIMUR",
  "name": "AMAITENG MULIA",
  "postalCode": "23891"
 },
 {
  "id": 1101020040,
  "districtId": 1101020,
  "districtName": "SIMEULUE TIMUR",
  "name": "AMERIA BAHAGIA",
  "postalCode": "23891"
 }
]