[
 {
  "id": 1109160001,
  "districtId": 1109160,
  "name": "TUHA SUWIEK"
 },
 {
  "id": 1109160002,
  "districtId": 1109160,
  "name": "MESJID SUWIEK"
 },
 {
  "id": 1109160003,
  "districtId": 1109160,
  "name": "TEUNGOH SUWIEK"
 },
 {
  "id": 1109160004,
  "districtId": 1109160,
  "name": "BEUREUDEUP"
 },
 {
  "id": 1109160005,
  "districtId": 1109160,
  "name": "SUKON ULGA"
 },
 {
  "id": 1109160006,
  "districtId": 1109160,
  "name": "PEUTOE"
 },
 {
  "id": 1109160007,
  "districtId": 1109160,
  "name": "GLEE GAPUI"
 },
 {
  "id": 1109160008,
  "districtId": 1109160,
  "name": "MESJID ULGA"
 },
 {
  "id": 1109160009,
  "districtId": 1109160,
  "name": "BLANG RAPAI"
 },
 {
  "id": 1109160010,
  "districtId": 1109160,
  "name": "BALEE BAROH GAPUI"
 },
 {
  "id": 1109160011,
  "districtId": 1109160,
  "name": "NEULOP II"
 },
 {
  "id": 1109160012,
  "districtId": 1109160,
  "name": "BARO GAPUI"
 },
 {
  "id": 1109160013,
  "districtId": 1109160,
  "name": "MESJID DIJIEM"
 },
 {
  "id": 1109160014,
  "districtId": 1109160,
  "name": "GUCI"
 },
 {
  "id": 1109160015,
  "districtId": 1109160,
  "name": "WAKEUEH"
 },
 {
  "id": 1109160016,
  "districtId": 1109160,
  "name": "DAYAH BIE"
 },
 {
  "id": 1109160017,
  "districtId": 1109160,
  "name": "JURONG"
 },
 {
  "id": 1109160018,
  "districtId": 1109160,
  "name": "BARO BLUEK"
 },
 {
  "id": 1109160019,
  "districtId": 1109160,
  "name": "RUMIA"
 },
 {
  "id": 1109160020,
  "districtId": 1109160,
  "name": "KEUTAPANG"
 },
 {
  "id": 1109160021,
  "districtId": 1109160,
  "name": "COT SEUKEE"
 },
 {
  "id": 1109160022,
  "districtId": 1109160,
  "name": "DRIEN"
 },
 {
  "id": 1109160023,
  "districtId": 1109160,
  "name": "BALE BAROH BLUEK"
 },
 {
  "id": 1109160024,
  "districtId": 1109160,
  "name": "TEUNGOH BLANG"
 },
 {
  "id": 1109160025,
  "districtId": 1109160,
  "name": "MEULAYU"
 },
 {
  "id": 1109160026,
  "districtId": 1109160,
  "name": "SUKON TUNGKOP"
 },
 {
  "id": 1109160027,
  "districtId": 1109160,
  "name": "KEUBANG"
 },
 {
  "id": 1109160028,
  "districtId": 1109160,
  "name": "GAROT CUT"
 },
 {
  "id": 1109160029,
  "districtId": 1109160,
  "name": "RAWA TUNGKOP"
 },
 {
  "id": 1109160030,
  "districtId": 1109160,
  "name": "MESJID TUNGKOP"
 },
 {
  "id": 1109160031,
  "districtId": 1109160,
  "name": "LAMREUNEUNG"
 },
 {
  "id": 1109160032,
  "districtId": 1109160,
  "name": "LAMKABU"
 },
 {
  "id": 1109160033,
  "districtId": 1109160,
  "name": "MESJID BARO"
 },
 {
  "id": 1109160034,
  "districtId": 1109160,
  "name": "TAMPIENG BAROH"
 },
 {
  "id": 1109160035,
  "districtId": 1109160,
  "name": "DAYAH CALEUE"
 },
 {
  "id": 1109160036,
  "districtId": 1109160,
  "name": "TAMPIENG TUNONG"
 },
 {
  "id": 1109160037,
  "districtId": 1109160,
  "name": "ULEE BIRAH"
 },
 {
  "id": 1109160038,
  "districtId": 1109160,
  "name": "BLANG LHOK KAJU"
 },
 {
  "id": 1109160039,
  "districtId": 1109160,
  "name": "BARO JRUEK"
 },
 {
  "id": 1109160040,
  "districtId": 1109160,
  "name": "MESJID LAM UJONG"
 },
 {
  "id": 1109160041,
  "districtId": 1109160,
  "name": "TUNGKOP CUT"
 },
 {
  "id": 1109160042,
  "districtId": 1109160,
  "name": "DAYAH MUARA GAROT"
 },
 {
  "id": 1109160043,
  "districtId": 1109160,
  "name": "BLANG GAROT"
 },
 {
  "id": 1109160044,
  "districtId": 1109160,
  "name": "PULO GAMPONG U"
 },
 {
  "id": 1109160045,
  "districtId": 1109160,
  "name": "DAYAH KEURAKO"
 },
 {
  "id": 1109160046,
  "districtId": 1109160,
  "name": "YUB MEE"
 },
 {
  "id": 1109160047,
  "districtId": 1109160,
  "name": "RAYA LHOK KAJU"
 },
 {
  "id": 1109160048,
  "districtId": 1109160,
  "name": "PANTE GAROT"
 },
 {
  "id": 1109160049,
  "districtId": 1109160,
  "name": "PANTE LHOK KAJU"
 }
]