[
 {
  "id": 1109220001,
  "districtId": 1109220,
  "districtName": "BATEE",
  "name": "KAREUNG",
  "postalCode": "24152"
 },
 {
  "id": 1109220002,
  "districtId": 1109220,
  "districtName": "BATEE",
  "name": "AWE",
  "postalCode": ""
 },
 {
  "id": 1109220003,
  "districtId": 1109220,
  "districtName": "BATEE",
  "name": "RUNGKOM",
  "postalCode": "24152"
 },
 {
  "id": 1109220004,
  "districtId": 1109220,
  "districtName": "BATEE",
  "name": "PULO PANDE",
  "postalCode": "24152"
 },
 {
  "id": 1109220005,
  "districtId": 1109220,
  "districtName": "BATEE",
  "name": "MEE",
  "postalCode": "24386"
 },
 {
  "id": 1109220006,
  "districtId": 1109220,
  "districtName": "BATEE",
  "name": "ALUE LADA",
  "postalCode": "24152"
 },
 {
  "id": 1109220007,
  "districtId": 1109220,
  "districtName": "BATEE",
  "name": "SEULATAN",
  "postalCode": "24152"
 },
 {
  "id": 1109220008,
  "districtId": 1109220,
  "districtName": "BATEE",
  "name": "TUHA",
  "postalCode": "24152"
 },
 {
  "id": 1109220009,
  "districtId": 1109220,
  "districtName": "BATEE",
  "name": "TEUPIN RAYA",
  "postalCode": "24152"
 },
 {
  "id": 1109220010,
  "districtId": 1109220,
  "districtName": "BATEE",
  "name": "CALONG CUT",
  "postalCode": "24152"
 },
 {
  "id": 1109220011,
  "districtId": 1109220,
  "districtName": "BATEE",
  "name": "DAYAH",
  "postalCode": "24152"
 },
 {
  "id": 1109220012,
  "districtId": 1109220,
  "districtName": "BATEE",
  "name": "MEUCAT",
  "postalCode": "24152"
 },
 {
  "id": 1109220013,
  "districtId": 1109220,
  "districtName": "BATEE",
  "name": "ARON",
  "postalCode": "24152"
 },
 {
  "id": 1109220014,
  "districtId": 1109220,
  "districtName": "BATEE",
  "name": "MESJID",
  "postalCode": "23681"
 },
 {
  "id": 1109220015,
  "districtId": 1109220,
  "districtName": "BATEE",
  "name": "BINTANG HU",
  "postalCode": "24152"
 },
 {
  "id": 1109220016,
  "districtId": 1109220,
  "districtName": "BATEE",
  "name": "DAYAH TUHA",
  "postalCode": "24186"
 },
 {
  "id": 1109220017,
  "districtId": 1109220,
  "districtName": "BATEE",
  "name": "DAYAH BAROH",
  "postalCode": "24152"
 },
 {
  "id": 1109220018,
  "districtId": 1109220,
  "districtName": "BATEE",
  "name": "PULO TUKOK",
  "postalCode": "24152"
 },
 {
  "id": 1109220019,
  "districtId": 1109220,
  "districtName": "BATEE",
  "name": "GLUMPANG LHEE",
  "postalCode": ""
 },
 {
  "id": 1109220020,
  "districtId": 1109220,
  "districtName": "BATEE",
  "name": "GEUNTENG TIMUR",
  "postalCode": "24152"
 },
 {
  "id": 1109220021,
  "districtId": 1109220,
  "districtName": "BATEE",
  "name": "GEUNTENG BARAT",
  "postalCode": "24152"
 },
 {
  "id": 1109220022,
  "districtId": 1109220,
  "districtName": "BATEE",
  "name": "PULO BUNGONG",
  "postalCode": "24152"
 },
 {
  "id": 1109220023,
  "districtId": 1109220,
  "districtName": "BATEE",
  "name": "TEUPIN JEUE",
  "postalCode": "24152"
 },
 {
  "id": 1109220024,
  "districtId": 1109220,
  "districtName": "BATEE",
  "name": "NEUHEUN",
  "postalCode": "24152"
 },
 {
  "id": 1109220025,
  "districtId": 1109220,
  "districtName": "BATEE",
  "name": "CRUENG",
  "postalCode": "24152"
 },
 {
  "id": 1109220026,
  "districtId": 1109220,
  "districtName": "BATEE",
  "name": "KULAM",
  "postalCode": "24152"
 },
 {
  "id": 1109220027,
  "districtId": 1109220,
  "districtName": "BATEE",
  "name": "KULEE",
  "postalCode": ""
 },
 {
  "id": 1109220028,
  "districtId": 1109220,
  "districtName": "BATEE",
  "name": "PASI BEURANDEH",
  "postalCode": ""
 }
]