[
 {
  "id": 1109080032,
  "districtId": 1109080,
  "districtName": "MUTIARA",
  "name": "PAYA TIBA",
  "postalCode": "24173"
 },
 {
  "id": 1109080033,
  "districtId": 1109080,
  "districtName": "MUTIARA",
  "name": "RAPANA",
  "postalCode": "24173"
 },
 {
  "id": 1109080034,
  "districtId": 1109080,
  "districtName": "MUTIARA",
  "name": "BARO YAMAN",
  "postalCode": "24173"
 },
 {
  "id": 1109080044,
  "districtId": 1109080,
  "districtName": "MUTIARA",
  "name": "SENTOSA",
  "postalCode": "24152"
 },
 {
  "id": 1109080045,
  "districtId": 1109080,
  "districtName": "MUTIARA",
  "name": "MESJID YAMAN",
  "postalCode": "24173"
 },
 {
  "id": 1109080046,
  "districtId": 1109080,
  "districtName": "MUTIARA",
  "name": "BAROH BARAT YAMAN",
  "postalCode": ""
 },
 {
  "id": 1109080047,
  "districtId": 1109080,
  "districtName": "MUTIARA",
  "name": "MEE TEUNGOH",
  "postalCode": ""
 },
 {
  "id": 1109080048,
  "districtId": 1109080,
  "districtName": "MUTIARA",
  "name": "BALE",
  "postalCode": "24373"
 },
 {
  "id": 1109080049,
  "districtId": 1109080,
  "districtName": "MUTIARA",
  "name": "LINGKOK",
  "postalCode": "24164"
 },
 {
  "id": 1109080050,
  "districtId": 1109080,
  "districtName": "MUTIARA",
  "name": "REULUI",
  "postalCode": ""
 },
 {
  "id": 1109080051,
  "districtId": 1109080,
  "districtName": "MUTIARA",
  "name": "DAYAH SYARIF",
  "postalCode": "24173"
 },
 {
  "id": 1109080052,
  "districtId": 1109080,
  "districtName": "MUTIARA",
  "name": "RIBEUN",
  "postalCode": ""
 },
 {
  "id": 1109080053,
  "districtId": 1109080,
  "districtName": "MUTIARA",
  "name": "PEUREULAK",
  "postalCode": "23671"
 },
 {
  "id": 1109080054,
  "districtId": 1109080,
  "districtName": "MUTIARA",
  "name": "KUMBANG",
  "postalCode": "24162"
 },
 {
  "id": 1109080055,
  "districtId": 1109080,
  "districtName": "MUTIARA",
  "name": "MEE PANYANG",
  "postalCode": ""
 },
 {
  "id": 1109080056,
  "districtId": 1109080,
  "districtName": "MUTIARA",
  "name": "BLANG LILEUE",
  "postalCode": "24173"
 },
 {
  "id": 1109080057,
  "districtId": 1109080,
  "districtName": "MUTIARA",
  "name": "BALE BARO KEUMANGAN",
  "postalCode": ""
 },
 {
  "id": 1109080058,
  "districtId": 1109080,
  "districtName": "MUTIARA",
  "name": "MESJID KEUMANGAN",
  "postalCode": "24173"
 },
 {
  "id": 1109080059,
  "districtId": 1109080,
  "districtName": "MUTIARA",
  "name": "LUENG SAGOE",
  "postalCode": "24173"
 },
 {
  "id": 1109080060,
  "districtId": 1109080,
  "districtName": "MUTIARA",
  "name": "BLANG BEUREUEH",
  "postalCode": "24173"
 },
 {
  "id": 1109080069,
  "districtId": 1109080,
  "districtName": "MUTIARA",
  "name": "LAMPOH SIRONG",
  "postalCode": ""
 },
 {
  "id": 1109080070,
  "districtId": 1109080,
  "districtName": "MUTIARA",
  "name": "PANTE BEUREUEH",
  "postalCode": "24173"
 },
 {
  "id": 1109080071,
  "districtId": 1109080,
  "districtName": "MUTIARA",
  "name": "PALOH KAMBUEK",
  "postalCode": ""
 },
 {
  "id": 1109080072,
  "districtId": 1109080,
  "districtName": "MUTIARA",
  "name": "DAYAH BEUREUEH",
  "postalCode": "24173"
 },
 {
  "id": 1109080073,
  "districtId": 1109080,
  "districtName": "MUTIARA",
  "name": "BLANG TIDIEK",
  "postalCode": "24173"
 },
 {
  "id": 1109080074,
  "districtId": 1109080,
  "districtName": "MUTIARA",
  "name": "JADAN",
  "postalCode": ""
 },
 {
  "id": 1109080075,
  "districtId": 1109080,
  "districtName": "MUTIARA",
  "name": "TUHA GAMPONG GAJAH",
  "postalCode": ""
 },
 {
  "id": 1109080076,
  "districtId": 1109080,
  "districtName": "MUTIARA",
  "name": "DAYAH TIDIEK",
  "postalCode": "24173"
 },
 {
  "id": 1109080077,
  "districtId": 1109080,
  "districtName": "MUTIARA",
  "name": "KEUMANGAN CUT",
  "postalCode": "24173"
 }
]