[
 {
  "id": 1277010001,
  "districtId": 1277010,
  "districtName": "PADANGSIDIMPUAN TENGGARA",
  "name": "SIHITANG",
  "postalCode": "22733"
 },
 {
  "id": 1277010002,
  "districtId": 1277010,
  "districtName": "PADANGSIDIMPUAN TENGGARA",
  "name": "PAL IV P KOLING",
  "postalCode": ""
 },
 {
  "id": 1277010003,
  "districtId": 1277010,
  "districtName": "PADANGSIDIMPUAN TENGGARA",
  "name": "SALAMBUE",
  "postalCode": "22742"
 },
 {
  "id": 1277010004,
  "districtId": 1277010,
  "districtName": "PADANGSIDIMPUAN TENGGARA",
  "name": "SIGULANG",
  "postalCode": "22733"
 },
 {
  "id": 1277010005,
  "districtId": 1277010,
  "districtName": "PADANGSIDIMPUAN TENGGARA",
  "name": "HUTA KOJE",
  "postalCode": ""
 },
 {
  "id": 1277010006,
  "districtId": 1277010,
  "districtName": "PADANGSIDIMPUAN TENGGARA",
  "name": "HUTA LIMBONG",
  "postalCode": "22733"
 },
 {
  "id": 1277010007,
  "districtId": 1277010,
  "districtName": "PADANGSIDIMPUAN TENGGARA",
  "name": "HUTA PADANG PK",
  "postalCode": ""
 },
 {
  "id": 1277010008,
  "districtId": 1277010,
  "districtName": "PADANGSIDIMPUAN TENGGARA",
  "name": "PIJOR KOLING",
  "postalCode": "22756"
 },
 {
  "id": 1277010009,
  "districtId": 1277010,
  "districtName": "PADANGSIDIMPUAN TENGGARA",
  "name": "GOTI",
  "postalCode": "22733"
 },
 {
  "id": 1277010010,
  "districtId": 1277010,
  "districtName": "PADANGSIDIMPUAN TENGGARA",
  "name": "MANEGEN",
  "postalCode": "22733"
 },
 {
  "id": 1277010011,
  "districtId": 1277010,
  "districtName": "PADANGSIDIMPUAN TENGGARA",
  "name": "MANUNGGANG JAE",
  "postalCode": "22733"
 },
 {
  "id": 1277010012,
  "districtId": 1277010,
  "districtName": "PADANGSIDIMPUAN TENGGARA",
  "name": "LABUHAN RASOKI",
  "postalCode": "22733"
 },
 {
  "id": 1277010013,
  "districtId": 1277010,
  "districtName": "PADANGSIDIMPUAN TENGGARA",
  "name": "PURBATUA P KOLING",
  "postalCode": ""
 },
 {
  "id": 1277010014,
  "districtId": 1277010,
  "districtName": "PADANGSIDIMPUAN TENGGARA",
  "name": "MANUNGGANG JULU",
  "postalCode": "22733"
 },
 {
  "id": 1277010015,
  "districtId": 1277010,
  "districtName": "PADANGSIDIMPUAN TENGGARA",
  "name": "TARUTUNG BARU",
  "postalCode": "22733"
 },
 {
  "id": 1277010016,
  "districtId": 1277010,
  "districtName": "PADANGSIDIMPUAN TENGGARA",
  "name": "HUTA LOMBANG",
  "postalCode": "22763"
 },
 {
  "id": 1277010017,
  "districtId": 1277010,
  "districtName": "PADANGSIDIMPUAN TENGGARA",
  "name": "PERKEBUNAN P KOLING",
  "postalCode": ""
 },
 {
  "id": 1277010018,
  "districtId": 1277010,
  "districtName": "PADANGSIDIMPUAN TENGGARA",
  "name": "LABUHAN LABO",
  "postalCode": "22733"
 }
]