[
 {
  "id": 1701050001,
  "districtId": 1701050,
  "name": "MUARA PULUTAN"
 },
 {
  "id": 1701050002,
  "districtId": 1701050,
  "name": "MUARA PAYANG"
 },
 {
  "id": 1701050003,
  "districtId": 1701050,
  "name": "DURIAN SEGINIM"
 },
 {
  "id": 1701050004,
  "districtId": 1701050,
  "name": "BANDING AGUNG"
 },
 {
  "id": 1701050005,
  "districtId": 1701050,
  "name": "PAJAR BULAN"
 },
 {
  "id": 1701050006,
  "districtId": 1701050,
  "name": "PADANG LEBAR"
 },
 {
  "id": 1701050007,
  "districtId": 1701050,
  "name": "DUSUN TENGAH"
 },
 {
  "id": 1701050008,
  "districtId": 1701050,
  "name": "PADANG SIRING"
 },
 {
  "id": 1701050009,
  "districtId": 1701050,
  "name": "TANJUNG MENANG"
 },
 {
  "id": 1701050010,
  "districtId": 1701050,
  "name": "GUNUNG AYU"
 },
 {
  "id": 1701050011,
  "districtId": 1701050,
  "name": "KOTA BUMI BARU"
 },
 {
  "id": 1701050012,
  "districtId": 1701050,
  "name": "SINDANG BULAN"
 },
 {
  "id": 1701050013,
  "districtId": 1701050,
  "name": "SUKARAJA"
 },
 {
  "id": 1701050014,
  "districtId": 1701050,
  "name": "PASAR BARU"
 },
 {
  "id": 1701050015,
  "districtId": 1701050,
  "name": "DARAT SAWAH"
 },
 {
  "id": 1701050016,
  "districtId": 1701050,
  "name": "KOTA AGUNG"
 },
 {
  "id": 1701050017,
  "districtId": 1701050,
  "name": "MUARA DANAU"
 },
 {
  "id": 1701050018,
  "districtId": 1701050,
  "name": "BABATAN ILIR"
 },
 {
  "id": 1701050019,
  "districtId": 1701050,
  "name": "BABATAN ULU"
 },
 {
  "id": 1701050020,
  "districtId": 1701050,
  "name": "TANJUNG AGUNG"
 },
 {
  "id": 1701050021,
  "districtId": 1701050,
  "name": "DUSUN BARU"
 },
 {
  "id": 1701050022,
  "districtId": 1701050,
  "name": "DARAT SAWAH ULU"
 }
]