[
 {
  "id": 1702042001,
  "districtId": 1702042,
  "name": "AIR MELES ATAS"
 },
 {
  "id": 1702042002,
  "districtId": 1702042,
  "name": "CAWANG BARU"
 },
 {
  "id": 1702042003,
  "districtId": 1702042,
  "name": "CAWANG LAMA"
 },
 {
  "id": 1702042004,
  "districtId": 1702042,
  "name": "KAYU MANIS"
 },
 {
  "id": 1702042005,
  "districtId": 1702042,
  "name": "SIMPANG NANGKA"
 },
 {
  "id": 1702042006,
  "districtId": 1702042,
  "name": "KAMPUNG BARU"
 },
 {
  "id": 1702042007,
  "districtId": 1702042,
  "name": "SUBAN AYAM"
 },
 {
  "id": 1702042008,
  "districtId": 1702042,
  "name": "AIR PUTIH KALI BANDUNG"
 },
 {
  "id": 1702042009,
  "districtId": 1702042,
  "name": "AIR DUKU"
 },
 {
  "id": 1702042010,
  "districtId": 1702042,
  "name": "SAMBIREJO"
 },
 {
  "id": 1702042011,
  "districtId": 1702042,
  "name": "SUMBER BENING"
 },
 {
  "id": 1702042012,
  "districtId": 1702042,
  "name": "SUMBER URIP"
 },
 {
  "id": 1702042013,
  "districtId": 1702042,
  "name": "KARANG JAYA"
 },
 {
  "id": 1702042014,
  "districtId": 1702042,
  "name": "KALI PADANG"
 },
 {
  "id": 1702042015,
  "districtId": 1702042,
  "name": "TALANG LAHAT"
 },
 {
  "id": 1702042016,
  "districtId": 1702042,
  "name": "MOJOREJO"
 }
]