[
 {
  "id": 1705051001,
  "districtId": 1705051,
  "name": "PASAR NGALAM"
 },
 {
  "id": 1705051002,
  "districtId": 1705051,
  "name": "SUKASARI"
 },
 {
  "id": 1705051003,
  "districtId": 1705051,
  "name": "TAWANG REJO"
 },
 {
  "id": 1705051004,
  "districtId": 1705051,
  "name": "KUNGKAI BARU"
 },
 {
  "id": 1705051005,
  "districtId": 1705051,
  "name": "KEBAN AGUNG"
 },
 {
  "id": 1705051006,
  "districtId": 1705051,
  "name": "LAWANG AGUNG"
 },
 {
  "id": 1705051007,
  "districtId": 1705051,
  "name": "PADANG PELASAN"
 },
 {
  "id": 1705051008,
  "districtId": 1705051,
  "name": "AIR PERIUKAN"
 },
 {
  "id": 1705051009,
  "districtId": 1705051,
  "name": "DERMAYU"
 },
 {
  "id": 1705051010,
  "districtId": 1705051,
  "name": "SUKA MAJU"
 },
 {
  "id": 1705051011,
  "districtId": 1705051,
  "name": "TALANG BENUANG"
 },
 {
  "id": 1705051012,
  "districtId": 1705051,
  "name": "TALANG ALAI"
 },
 {
  "id": 1705051013,
  "districtId": 1705051,
  "name": "LUBUK GILANG"
 },
 {
  "id": 1705051014,
  "districtId": 1705051,
  "name": "TALANG SEBARIS"
 },
 {
  "id": 1705051015,
  "districtId": 1705051,
  "name": "LOKASI BARU"
 },
 {
  "id": 1705051016,
  "districtId": 1705051,
  "name": "TABA LUBUK PUDING"
 }
]