[
 {
  "id": 1805040017,
  "districtId": 1805040,
  "districtName": "GUNUNG SUGIH",
  "name": "TERBANGGI SUBING",
  "postalCode": "34161"
 },
 {
  "id": 1805040018,
  "districtId": 1805040,
  "districtName": "GUNUNG SUGIH",
  "name": "WONO SARI",
  "postalCode": "24478"
 },
 {
  "id": 1805040019,
  "districtId": 1805040,
  "districtName": "GUNUNG SUGIH",
  "name": "TERBANGGI AGUNG",
  "postalCode": "34161"
 },
 {
  "id": 1805040020,
  "districtId": 1805040,
  "districtName": "GUNUNG SUGIH",
  "name": "GUNUNG SUGIH RAYA",
  "postalCode": "34161"
 },
 {
  "id": 1805040021,
  "districtId": 1805040,
  "districtName": "GUNUNG SUGIH",
  "name": "KOMERING AGUNG",
  "postalCode": "34161"
 },
 {
  "id": 1805040022,
  "districtId": 1805040,
  "districtName": "GUNUNG SUGIH",
  "name": "KOMERING PUTIH",
  "postalCode": "34161"
 },
 {
  "id": 1805040023,
  "districtId": 1805040,
  "districtName": "GUNUNG SUGIH",
  "name": "PAJAR BULAN",
  "postalCode": "32279"
 },
 {
  "id": 1805040024,
  "districtId": 1805040,
  "districtName": "GUNUNG SUGIH",
  "name": "SEPUTIH JAYA",
  "postalCode": "34161"
 },
 {
  "id": 1805040025,
  "districtId": 1805040,
  "districtName": "GUNUNG SUGIH",
  "name": "GUNUNG SARI",
  "postalCode": "28471"
 },
 {
  "id": 1805040026,
  "districtId": 1805040,
  "districtName": "GUNUNG SUGIH",
  "name": "GUNUNG SUGIH",
  "postalCode": "32386"
 },
 {
  "id": 1805040027,
  "districtId": 1805040,
  "districtName": "GUNUNG SUGIH",
  "name": "BUYUT UDIK",
  "postalCode": "34161"
 },
 {
  "id": 1805040028,
  "districtId": 1805040,
  "districtName": "GUNUNG SUGIH",
  "name": "PUTRA BUYUT",
  "postalCode": "34161"
 },
 {
  "id": 1805040029,
  "districtId": 1805040,
  "districtName": "GUNUNG SUGIH",
  "name": "BUYUT ILIR",
  "postalCode": "34161"
 },
 {
  "id": 1805040030,
  "districtId": 1805040,
  "districtName": "GUNUNG SUGIH",
  "name": "BUYUT UTARA",
  "postalCode": "34161"
 },
 {
  "id": 1805040031,
  "districtId": 1805040,
  "districtName": "GUNUNG SUGIH",
  "name": "BANGUN REJO",
  "postalCode": "21454"
 }
]