[
 {
  "id": 2103060001,
  "districtId": 2103060,
  "name": "KAMPUNG HILIR"
 },
 {
  "id": 2103060002,
  "districtId": 2103060,
  "name": "SERASAN"
 },
 {
  "id": 2103060005,
  "districtId": 2103060,
  "name": "BATU BERIAN"
 },
 {
  "id": 2103060006,
  "districtId": 2103060,
  "name": "TANJUNG SETELUNG"
 },
 {
  "id": 2103060007,
  "districtId": 2103060,
  "name": "TANJUNG BALAU"
 },
 {
  "id": 2103060008,
  "districtId": 2103060,
  "name": "PANGKALAN"
 },
 {
  "id": 2103060009,
  "districtId": 2103060,
  "name": "JERMALIK"
 }
]