[
 {
  "id": 3202280001,
  "districtId": 3202280,
  "districtName": "CIKIDANG",
  "name": "SAMPORA",
  "postalCode": "43367"
 },
 {
  "id": 3202280002,
  "districtId": 3202280,
  "districtName": "CIKIDANG",
  "name": "CIJAMBE",
  "postalCode": "41286"
 },
 {
  "id": 3202280003,
  "districtId": 3202280,
  "districtName": "CIKIDANG",
  "name": "CIKIRAY",
  "postalCode": "43367"
 },
 {
  "id": 3202280004,
  "districtId": 3202280,
  "districtName": "CIKIDANG",
  "name": "MEKARNANGKA",
  "postalCode": "43367"
 },
 {
  "id": 3202280005,
  "districtId": 3202280,
  "districtName": "CIKIDANG",
  "name": "CIKIDANG",
  "postalCode": "45464"
 },
 {
  "id": 3202280006,
  "districtId": 3202280,
  "districtName": "CIKIDANG",
  "name": "GUNUNG MALANG",
  "postalCode": "43367"
 },
 {
  "id": 3202280007,
  "districtId": 3202280,
  "districtName": "CIKIDANG",
  "name": "NANGKAKONENG",
  "postalCode": "43367"
 },
 {
  "id": 3202280008,
  "districtId": 3202280,
  "districtName": "CIKIDANG",
  "name": "PANGKALAN",
  "postalCode": "24477"
 },
 {
  "id": 3202280009,
  "districtId": 3202280,
  "districtName": "CIKIDANG",
  "name": "BUMISARI",
  "postalCode": "35362"
 },
 {
  "id": 3202280010,
  "districtId": 3202280,
  "districtName": "CIKIDANG",
  "name": "CICAREUH",
  "postalCode": "43367"
 },
 {
  "id": 3202280011,
  "districtId": 3202280,
  "districtName": "CIKIDANG",
  "name": "TAMANSARI",
  "postalCode": "35366"
 },
 {
  "id": 3202280012,
  "districtId": 3202280,
  "districtName": "CIKIDANG",
  "name": "CIKARAE THOYIBAH",
  "postalCode": ""
 }
]