[
 {
  "id": 3206140003,
  "districtId": 3206140,
  "name": "MANDALAHAYU"
 },
 {
  "id": 3206140004,
  "districtId": 3206140,
  "name": "KARYAMANDALA"
 },
 {
  "id": 3206140005,
  "districtId": 3206140,
  "name": "MULYASARI"
 },
 {
  "id": 3206140006,
  "districtId": 3206140,
  "name": "TANJUNGSARI"
 },
 {
  "id": 3206140007,
  "districtId": 3206140,
  "name": "MANDALAGUNA"
 },
 {
  "id": 3206140008,
  "districtId": 3206140,
  "name": "KAWITAN"
 },
 {
  "id": 3206140009,
  "districtId": 3206140,
  "name": "MANDALAWANGI"
 },
 {
  "id": 3206140010,
  "districtId": 3206140,
  "name": "BANJARWARINGIN"
 },
 {
  "id": 3206140018,
  "districtId": 3206140,
  "name": "KARYAWANGI"
 }
]