[
 {
  "id": 3212170001,
  "districtId": 3212170,
  "name": "KIAJARAN KULON"
 },
 {
  "id": 3212170002,
  "districtId": 3212170,
  "name": "KIJARAN WETAN"
 },
 {
  "id": 3212170003,
  "districtId": 3212170,
  "name": "LANJAN"
 },
 {
  "id": 3212170004,
  "districtId": 3212170,
  "name": "LANGUT"
 },
 {
  "id": 3212170005,
  "districtId": 3212170,
  "name": "LARANGAN"
 },
 {
  "id": 3212170006,
  "districtId": 3212170,
  "name": "WARU"
 },
 {
  "id": 3212170007,
  "districtId": 3212170,
  "name": "LEGOK"
 },
 {
  "id": 3212170008,
  "districtId": 3212170,
  "name": "BOJONGSLAWI"
 },
 {
  "id": 3212170009,
  "districtId": 3212170,
  "name": "LOHBENER"
 },
 {
  "id": 3212170010,
  "districtId": 3212170,
  "name": "PAMAYAHAN"
 },
 {
  "id": 3212170011,
  "districtId": 3212170,
  "name": "SINDANGKERTA"
 },
 {
  "id": 3212170015,
  "districtId": 3212170,
  "name": "RAMBATAN KULON"
 }
]