[
 {
  "id": 3212190002,
  "districtId": 3212190,
  "name": "PRANTI"
 },
 {
  "id": 3212190003,
  "districtId": 3212190,
  "name": "WIRAKANAN"
 },
 {
  "id": 3212190004,
  "districtId": 3212190,
  "name": "KARANGMULYA"
 },
 {
  "id": 3212190005,
  "districtId": 3212190,
  "name": "KARANGANYAR"
 },
 {
  "id": 3212190006,
  "districtId": 3212190,
  "name": "WIRAPANJUNAN"
 },
 {
  "id": 3212190007,
  "districtId": 3212190,
  "name": "PAREAN GIRANG"
 },
 {
  "id": 3212190008,
  "districtId": 3212190,
  "name": "BULAK"
 },
 {
  "id": 3212190009,
  "districtId": 3212190,
  "name": "ILIR"
 },
 {
  "id": 3212190010,
  "districtId": 3212190,
  "name": "SOGE"
 },
 {
  "id": 3212190011,
  "districtId": 3212190,
  "name": "ERETAN WETAN"
 },
 {
  "id": 3212190012,
  "districtId": 3212190,
  "name": "ERETAN KULON"
 },
 {
  "id": 3212190013,
  "districtId": 3212190,
  "name": "KERTAWINANGUN"
 }
]