[
 {
  "id": 3215072001,
  "districtId": 3215072,
  "name": "SARIMULYA"
 },
 {
  "id": 3215072002,
  "districtId": 3215072,
  "name": "JOMIN BARAT"
 },
 {
  "id": 3215072003,
  "districtId": 3215072,
  "name": "JOMIN TIMUR"
 },
 {
  "id": 3215072004,
  "districtId": 3215072,
  "name": "PANGULAH SELATAN"
 },
 {
  "id": 3215072005,
  "districtId": 3215072,
  "name": "PANGULAH UTARA"
 },
 {
  "id": 3215072006,
  "districtId": 3215072,
  "name": "PANGULAH BARU"
 },
 {
  "id": 3215072007,
  "districtId": 3215072,
  "name": "WANCIMEKAR"
 },
 {
  "id": 3215072009,
  "districtId": 3215072,
  "name": "CIKAMPEK UTARA"
 }
]