[
 {
  "id": 3216150001,
  "districtId": 3216150,
  "districtName": "MUARA GEMBONG",
  "name": "PANTAI HARAPANJAYA",
  "postalCode": ""
 },
 {
  "id": 3216150002,
  "districtId": 3216150,
  "districtName": "MUARA GEMBONG",
  "name": "PANTAIMEKAR",
  "postalCode": ""
 },
 {
  "id": 3216150003,
  "districtId": 3216150,
  "districtName": "MUARA GEMBONG",
  "name": "PANTAI SEDERHANA",
  "postalCode": "17730"
 },
 {
  "id": 3216150004,
  "districtId": 3216150,
  "districtName": "MUARA GEMBONG",
  "name": "PANTAIBAKTI",
  "postalCode": ""
 },
 {
  "id": 3216150005,
  "districtId": 3216150,
  "districtName": "MUARA GEMBONG",
  "name": "PANTAIBAHAGIA",
  "postalCode": ""
 },
 {
  "id": 3216150006,
  "districtId": 3216150,
  "districtName": "MUARA GEMBONG",
  "name": "JAYASAKTI",
  "postalCode": "17730"
 }
]