[
 {
  "id": 3301130002,
  "districtId": 3301130,
  "name": "TRITIH WETAN"
 },
 {
  "id": 3301130003,
  "districtId": 3301130,
  "name": "TRITIH LOR"
 },
 {
  "id": 3301130004,
  "districtId": 3301130,
  "name": "SUMINGKIR"
 },
 {
  "id": 3301130005,
  "districtId": 3301130,
  "name": "JERUKLEGI WETAN"
 },
 {
  "id": 3301130006,
  "districtId": 3301130,
  "name": "JERUKLEGI KULON"
 },
 {
  "id": 3301130007,
  "districtId": 3301130,
  "name": "SAWANGAN"
 },
 {
  "id": 3301130008,
  "districtId": 3301130,
  "name": "CILIBANG"
 },
 {
  "id": 3301130009,
  "districtId": 3301130,
  "name": "MENDALA"
 },
 {
  "id": 3301130010,
  "districtId": 3301130,
  "name": "KARANGKEMIRI"
 },
 {
  "id": 3301130011,
  "districtId": 3301130,
  "name": "JAMBUSARI"
 },
 {
  "id": 3301130012,
  "districtId": 3301130,
  "name": "PRAPAGAN"
 },
 {
  "id": 3301130013,
  "districtId": 3301130,
  "name": "CITEPUS"
 }
]