[
 {
  "id": 3313140001,
  "districtId": 3313140,
  "name": "KEMIRI"
 },
 {
  "id": 3313140002,
  "districtId": 3313140,
  "name": "NANGSRI"
 },
 {
  "id": 3313140003,
  "districtId": 3313140,
  "name": "MACANAN"
 },
 {
  "id": 3313140004,
  "districtId": 3313140,
  "name": "ALASTUWO"
 },
 {
  "id": 3313140005,
  "districtId": 3313140,
  "name": "BANJARHARJO"
 },
 {
  "id": 3313140006,
  "districtId": 3313140,
  "name": "MALANGGATEN"
 },
 {
  "id": 3313140007,
  "districtId": 3313140,
  "name": "KALIWULUH"
 },
 {
  "id": 3313140008,
  "districtId": 3313140,
  "name": "PULOSARI"
 },
 {
  "id": 3313140009,
  "districtId": 3313140,
  "name": "KEBAK"
 },
 {
  "id": 3313140010,
  "districtId": 3313140,
  "name": "WARU"
 }
]