[
 {
  "id": 3511010,
  "regencieId": 3511,
  "regencieName": "KABUPATEN BONDOWOSO",
  "name": "MAESAN"
 },
 {
  "id": 3511020,
  "regencieId": 3511,
  "regencieName": "KABUPATEN BONDOWOSO",
  "name": "GRUJUGAN"
 },
 {
  "id": 3511030,
  "regencieId": 3511,
  "regencieName": "KABUPATEN BONDOWOSO",
  "name": "TAMANAN"
 },
 {
  "id": 3511031,
  "regencieId": 3511,
  "regencieName": "KABUPATEN BONDOWOSO",
  "name": "JAMBESARI DARUS SHOLAH"
 },
 {
  "id": 3511040,
  "regencieId": 3511,
  "regencieName": "KABUPATEN BONDOWOSO",
  "name": "PUJER"
 },
 {
  "id": 3511050,
  "regencieId": 3511,
  "regencieName": "KABUPATEN BONDOWOSO",
  "name": "TLOGOSARI"
 },
 {
  "id": 3511060,
  "regencieId": 3511,
  "regencieName": "KABUPATEN BONDOWOSO",
  "name": "SUKOSARI"
 },
 {
  "id": 3511061,
  "regencieId": 3511,
  "regencieName": "KABUPATEN BONDOWOSO",
  "name": "SUMBER WRINGIN"
 },
 {
  "id": 3511070,
  "regencieId": 3511,
  "regencieName": "KABUPATEN BONDOWOSO",
  "name": "TAPEN"
 },
 {
  "id": 3511080,
  "regencieId": 3511,
  "regencieName": "KABUPATEN BONDOWOSO",
  "name": "WONOSARI"
 },
 {
  "id": 3511090,
  "regencieId": 3511,
  "regencieName": "KABUPATEN BONDOWOSO",
  "name": "TENGGARANG"
 },
 {
  "id": 3511100,
  "regencieId": 3511,
  "regencieName": "KABUPATEN BONDOWOSO",
  "name": "BONDOWOSO"
 },
 {
  "id": 3511110,
  "regencieId": 3511,
  "regencieName": "KABUPATEN BONDOWOSO",
  "name": "CURAH DAMI"
 },
 {
  "id": 3511111,
  "regencieId": 3511,
  "regencieName": "KABUPATEN BONDOWOSO",
  "name": "BINAKAL"
 },
 {
  "id": 3511120,
  "regencieId": 3511,
  "regencieName": "KABUPATEN BONDOWOSO",
  "name": "PAKEM"
 },
 {
  "id": 3511130,
  "regencieId": 3511,
  "regencieName": "KABUPATEN BONDOWOSO",
  "name": "WRINGIN"
 },
 {
  "id": 3511140,
  "regencieId": 3511,
  "regencieName": "KABUPATEN BONDOWOSO",
  "name": "TEGALAMPEL"
 },
 {
  "id": 3511141,
  "regencieId": 3511,
  "regencieName": "KABUPATEN BONDOWOSO",
  "name": "TAMAN KROCOK"
 },
 {
  "id": 3511150,
  "regencieId": 3511,
  "regencieName": "KABUPATEN BONDOWOSO",
  "name": "KLABANG"
 },
 {
  "id": 3511151,
  "regencieId": 3511,
  "regencieName": "KABUPATEN BONDOWOSO",
  "name": "IJEN"
 },
 {
  "id": 3511152,
  "regencieId": 3511,
  "regencieName": "KABUPATEN BONDOWOSO",
  "name": "BOTOLINGGO"
 },
 {
  "id": 3511160,
  "regencieId": 3511,
  "regencieName": "KABUPATEN BONDOWOSO",
  "name": "PRAJEKAN"
 },
 {
  "id": 3511170,
  "regencieId": 3511,
  "regencieName": "KABUPATEN BONDOWOSO",
  "name": "CERMEE"
 }
]