[
 {
  "id": 3514040001,
  "districtId": 3514040,
  "name": "KANDANGAN"
 },
 {
  "id": 3514040002,
  "districtId": 3514040,
  "name": "MOROREJO"
 },
 {
  "id": 3514040003,
  "districtId": 3514040,
  "name": "NGADIWONO"
 },
 {
  "id": 3514040004,
  "districtId": 3514040,
  "name": "PODOKOYO"
 },
 {
  "id": 3514040005,
  "districtId": 3514040,
  "name": "WONOKITRI"
 },
 {
  "id": 3514040006,
  "districtId": 3514040,
  "name": "TOSARI"
 },
 {
  "id": 3514040007,
  "districtId": 3514040,
  "name": "BALEDONO"
 },
 {
  "id": 3514040008,
  "districtId": 3514040,
  "name": "SEDAENG"
 }
]