[
 {
  "id": 3519030001,
  "districtId": 3519030,
  "name": "LEMBAH"
 },
 {
  "id": 3519030002,
  "districtId": 3519030,
  "name": "MLILIR"
 },
 {
  "id": 3519030003,
  "districtId": 3519030,
  "name": "KRADINAN"
 },
 {
  "id": 3519030005,
  "districtId": 3519030,
  "name": "BLIMBING"
 },
 {
  "id": 3519030006,
  "districtId": 3519030,
  "name": "BADER"
 },
 {
  "id": 3519030007,
  "districtId": 3519030,
  "name": "CANDIMULYO"
 },
 {
  "id": 3519030008,
  "districtId": 3519030,
  "name": "GLONGGONG"
 },
 {
  "id": 3519030009,
  "districtId": 3519030,
  "name": "DOLOPO"
 },
 {
  "id": 3519030010,
  "districtId": 3519030,
  "name": "DOHO"
 },
 {
  "id": 3519030011,
  "districtId": 3519030,
  "name": "KETAWANG"
 },
 {
  "id": 3519030012,
  "districtId": 3519030,
  "name": "BANGUNSARI"
 }
]