[
 {
  "id": 3523150001,
  "districtId": 3523150,
  "name": "KAPU"
 },
 {
  "id": 3523150002,
  "districtId": 3523150,
  "name": "TEGALREJO"
 },
 {
  "id": 3523150003,
  "districtId": 3523150,
  "name": "TAHULU"
 },
 {
  "id": 3523150004,
  "districtId": 3523150,
  "name": "MANDIREJO"
 },
 {
  "id": 3523150005,
  "districtId": 3523150,
  "name": "BOGOREJO"
 },
 {
  "id": 3523150006,
  "districtId": 3523150,
  "name": "SUMBEREJO"
 },
 {
  "id": 3523150007,
  "districtId": 3523150,
  "name": "SENDANGHAJI"
 },
 {
  "id": 3523150008,
  "districtId": 3523150,
  "name": "SAMBONGGEDE"
 },
 {
  "id": 3523150010,
  "districtId": 3523150,
  "name": "TUWIRI WETAN"
 },
 {
  "id": 3523150011,
  "districtId": 3523150,
  "name": "TUWIRI KULON"
 },
 {
  "id": 3523150012,
  "districtId": 3523150,
  "name": "BOREHBANGLE"
 },
 {
  "id": 3523150013,
  "districtId": 3523150,
  "name": "SENORI"
 },
 {
  "id": 3523150014,
  "districtId": 3523150,
  "name": "SEMBUNGREJO"
 },
 {
  "id": 3523150015,
  "districtId": 3523150,
  "name": "PONGPONGAN"
 },
 {
  "id": 3523150016,
  "districtId": 3523150,
  "name": "TEMANDANG"
 },
 {
  "id": 3523150017,
  "districtId": 3523150,
  "name": "TLOGOWARU"
 },
 {
  "id": 3523150018,
  "districtId": 3523150,
  "name": "TOBO"
 },
 {
  "id": 3523150019,
  "districtId": 3523150,
  "name": "SUGIHAN"
 }
]