[
 {
  "id": 5305062001,
  "districtId": 5305062,
  "districtName": "BIBOKI FEOTLEU",
  "name": "MANUMEAN",
  "postalCode": "85682"
 },
 {
  "id": 5305062002,
  "districtId": 5305062,
  "districtName": "BIBOKI FEOTLEU",
  "name": "KULUAN",
  "postalCode": "85682"
 },
 {
  "id": 5305062003,
  "districtId": 5305062,
  "districtName": "BIBOKI FEOTLEU",
  "name": "NAKU",
  "postalCode": "85682"
 },
 {
  "id": 5305062004,
  "districtId": 5305062,
  "districtName": "BIBOKI FEOTLEU",
  "name": "MAKUN",
  "postalCode": "85682"
 },
 {
  "id": 5305062005,
  "districtId": 5305062,
  "districtName": "BIBOKI FEOTLEU",
  "name": "BIRUNATUN",
  "postalCode": "85682"
 }
]