[
 {
  "id": 6404053001,
  "districtId": 6404053,
  "name": "CIPTA GRAHA"
 },
 {
  "id": 6404053002,
  "districtId": 6404053,
  "name": "BUMI JAYA"
 },
 {
  "id": 6404053003,
  "districtId": 6404053,
  "name": "BUMI RAPAK"
 },
 {
  "id": 6404053004,
  "districtId": 6404053,
  "name": "BUMI ETAM"
 },
 {
  "id": 6404053005,
  "districtId": 6404053,
  "name": "MATA AIR"
 },
 {
  "id": 6404053006,
  "districtId": 6404053,
  "name": "BUKIT PERMATA"
 },
 {
  "id": 6404053007,
  "districtId": 6404053,
  "name": "KADUNGAN JAYA"
 },
 {
  "id": 6404053008,
  "districtId": 6404053,
  "name": "PENGADAN BARU"
 }
]