[
 {
  "id": 7107020001,
  "districtId": 7107020,
  "districtName": "BINTAUNA",
  "name": "MOME",
  "postalCode": "95763"
 },
 {
  "id": 7107020003,
  "districtId": 7107020,
  "districtName": "BINTAUNA",
  "name": "PIMPI",
  "postalCode": "95763"
 },
 {
  "id": 7107020004,
  "districtId": 7107020,
  "districtName": "BINTAUNA",
  "name": "BUNIA",
  "postalCode": "95763"
 },
 {
  "id": 7107020005,
  "districtId": 7107020,
  "districtName": "BINTAUNA",
  "name": "KOPI",
  "postalCode": "95763"
 },
 {
  "id": 7107020006,
  "districtId": 7107020,
  "districtName": "BINTAUNA",
  "name": "BINTAUNA PANTE",
  "postalCode": ""
 },
 {
  "id": 7107020007,
  "districtId": 7107020,
  "districtName": "BINTAUNA",
  "name": "MINANGA",
  "postalCode": "95763"
 },
 {
  "id": 7107020008,
  "districtId": 7107020,
  "districtName": "BINTAUNA",
  "name": "BATULINTIK",
  "postalCode": "95763"
 },
 {
  "id": 7107020009,
  "districtId": 7107020,
  "districtName": "BINTAUNA",
  "name": "BINTAUNA",
  "postalCode": "95763"
 },
 {
  "id": 7107020010,
  "districtId": 7107020,
  "districtName": "BINTAUNA",
  "name": "TALAGA",
  "postalCode": "43154"
 },
 {
  "id": 7107020011,
  "districtId": 7107020,
  "districtName": "BINTAUNA",
  "name": "VOA'A",
  "postalCode": ""
 },
 {
  "id": 7107020012,
  "districtId": 7107020,
  "districtName": "BINTAUNA",
  "name": "PADANG",
  "postalCode": "23762"
 },
 {
  "id": 7107020013,
  "districtId": 7107020,
  "districtName": "BINTAUNA",
  "name": "KUHANGA",
  "postalCode": "95763"
 },
 {
  "id": 7107020014,
  "districtId": 7107020,
  "districtName": "BINTAUNA",
  "name": "BUNONG",
  "postalCode": "95763"
 },
 {
  "id": 7107020015,
  "districtId": 7107020,
  "districtName": "BINTAUNA",
  "name": "PADANG BARAT",
  "postalCode": "95763"
 },
 {
  "id": 7107020016,
  "districtId": 7107020,
  "districtName": "BINTAUNA",
  "name": "VAHUTA",
  "postalCode": "95763"
 }
]