[
 {
  "id": 7471013006,
  "districtId": 7471013,
  "districtName": "KADIA",
  "name": "KADIA",
  "postalCode": "93117"
 },
 {
  "id": 7471013009,
  "districtId": 7471013,
  "districtName": "KADIA",
  "name": "ANAIWOI",
  "postalCode": "93118"
 },
 {
  "id": 7471013010,
  "districtId": 7471013,
  "districtName": "KADIA",
  "name": "WOWAWANGGU",
  "postalCode": "93117"
 },
 {
  "id": 7471013012,
  "districtId": 7471013,
  "districtName": "KADIA",
  "name": "PONDAMBEA",
  "postalCode": "93117"
 }
]