[
 {
  "id": 7602050001,
  "districtId": 7602050,
  "name": "DARMA"
 },
 {
  "id": 7602050002,
  "districtId": 7602050,
  "name": "MANDING"
 },
 {
  "id": 7602050003,
  "districtId": 7602050,
  "name": "MADATTE"
 },
 {
  "id": 7602050004,
  "districtId": 7602050,
  "name": "PEKKABATA"
 },
 {
  "id": 7602050005,
  "districtId": 7602050,
  "name": "TAKATIDUNG"
 },
 {
  "id": 7602050006,
  "districtId": 7602050,
  "name": "LANTORA"
 },
 {
  "id": 7602050007,
  "districtId": 7602050,
  "name": "SULEWATANG"
 },
 {
  "id": 7602050008,
  "districtId": 7602050,
  "name": "WATTANG"
 },
 {
  "id": 7602050009,
  "districtId": 7602050,
  "name": "POLEWALI"
 }
]