[
 {
  "id": 9408071002,
  "districtId": 9408071,
  "districtName": "WONAWA",
  "name": "WOINAP",
  "postalCode": "98253"
 },
 {
  "id": 9408071003,
  "districtId": 9408071,
  "districtName": "WONAWA",
  "name": "KANAKI",
  "postalCode": "98253"
 },
 {
  "id": 9408071004,
  "districtId": 9408071,
  "districtName": "WONAWA",
  "name": "DUMANI",
  "postalCode": "98253"
 },
 {
  "id": 9408071005,
  "districtId": 9408071,
  "districtName": "WONAWA",
  "name": "WOOI",
  "postalCode": "97792"
 },
 {
  "id": 9408071006,
  "districtId": 9408071,
  "districtName": "WONAWA",
  "name": "AIBONDENI",
  "postalCode": "98253"
 },
 {
  "id": 9408071007,
  "districtId": 9408071,
  "districtName": "WONAWA",
  "name": "KAREMONI",
  "postalCode": "98253"
 },
 {
  "id": 9408071008,
  "districtId": 9408071,
  "districtName": "WONAWA",
  "name": "REMBAI",
  "postalCode": "98253"
 },
 {
  "id": 9408071009,
  "districtId": 9408071,
  "districtName": "WONAWA",
  "name": "HAIHOREI",
  "postalCode": "98253"
 },
 {
  "id": 9408071010,
  "districtId": 9408071,
  "districtName": "WONAWA",
  "name": "JAMARIA",
  "postalCode": ""
 },
 {
  "id": 9408071011,
  "districtId": 9408071,
  "districtName": "WONAWA",
  "name": "AWADO",
  "postalCode": "98253"
 }
]