[
 {
  "id": 9418021001,
  "districtId": 9418021,
  "name": "DOGE"
 },
 {
  "id": 9418021002,
  "districtId": 9418021,
  "name": "TIRI"
 },
 {
  "id": 9418021003,
  "districtId": 9418021,
  "name": "YEMARIMA"
 },
 {
  "id": 9418021004,
  "districtId": 9418021,
  "name": "DUGI"
 },
 {
  "id": 9418021005,
  "districtId": 9418021,
  "name": "TIGIKUN"
 },
 {
  "id": 9418021009,
  "districtId": 9418021,
  "name": "GOYAGE"
 },
 {
  "id": 9418021010,
  "districtId": 9418021,
  "name": "BENARI"
 },
 {
  "id": 9418021011,
  "districtId": 9418021,
  "name": "WIJAMURIK"
 },
 {
  "id": 9418021012,
  "districtId": 9418021,
  "name": "TIGIR"
 },
 {
  "id": 9418021013,
  "districtId": 9418021,
  "name": "BOPA"
 },
 {
  "id": 9418021014,
  "districtId": 9418021,
  "name": "ANGKASA"
 },
 {
  "id": 9418021015,
  "districtId": 9418021,
  "name": "GILOK"
 },
 {
  "id": 9418021016,
  "districtId": 9418021,
  "name": "WOJI"
 },
 {
  "id": 9418021017,
  "districtId": 9418021,
  "name": "MAMPULAGA"
 },
 {
  "id": 9418021018,
  "districtId": 9418021,
  "name": "TIDUR MABUK"
 },
 {
  "id": 9418021019,
  "districtId": 9418021,
  "name": "BINI"
 },
 {
  "id": 9418021020,
  "districtId": 9418021,
  "name": "DIDELONIK"
 },
 {
  "id": 9418021022,
  "districtId": 9418021,
  "name": "PEKO"
 }
]